pyiris/__init__.py
pyiris/iris.py
pyiris-0.0.2.dist-info/LICENSE
pyiris-0.0.2.dist-info/METADATA
pyiris-0.0.2.dist-info/WHEEL
pyiris-0.0.2.dist-info/top_level.txt
pyiris-0.0.2.dist-info/RECORD
