Metadata-Version: 2.1
Name: pyiris
Version: 0.0.2
Summary: IRIS Python API
Home-page: https://github.com/jungwonkim/iris
Author: Jungwon Kim
Author-email: kimj@ieee.org
License: UNKNOWN
Project-URL: Bug Tracker, https://github.com/jungwonkim/iris/issues
Platform: UNKNOWN
Classifier: Programming Language :: Python :: 3
Classifier: License :: OSI Approved :: BSD License
Classifier: Operating System :: POSIX :: Linux
Requires-Python: >=3.6
License-File: LICENSE
